{
  "name": "aggressive_caterpillar",
  "origin": "Factory",
  "tune": 46.016003,
  "waveform": 5,
  "sweep": 213.8005,
  "pitch_decay": 81.28909,
  "drive": 0.35279986,
  "drive_model": 2,
  "tex_amt": 0.43260005,
  "tex_decay": 42.388977,
  "tex_variation": 0.8694001,
  "analog_variation": 0.0,
  "tex_type": 3,
  "tex_tone": 0.19079989,
  "attack": 0.1,
  "decay": 227.45665,
  "sustain": 0.46242774,
  "release": 251.56073,
  "corrosion_frequency": 0.353,
  "corrosion_width": 1.8649604,
  "corrosion_noise_blend": 0.2104002,
  "corrosion_stereo": 0.8358001,
  "corrosion_amount": 0.41160014,
  "bass_synth_mode": false,
  "nam_active": false,
  "nam_input_gain": 0.0,
  "output_gain": 0.0,
  "nam_model": "PhilipsEL3541D",
  "categories": [
    "Kick2"
  ],
  "filter_active": true,
  "filter_type": "HP24",
  "filter_position": "PostNam",
  "filter_cutoff": 37.568146,
  "filter_resonance": 0.23519973,
  "filter_env_amount": -0.032000303,
  "filter_env_attack": 0.1,
  "filter_env_decay": 230.0,
  "filter_env_sustain": 0.0,
  "filter_env_release": 200.0,
  "filter_env_trigger": true,
  "filter_drive": 0.0,
  "filter_key_track": 0.0,
  "filter_wet_dry": 1.0
}
